tts_webui_extension/vox_cpm/__init__.py
tts_webui_extension/vox_cpm/main.py
tts_webui_extension/vox_cpm/ui.py
tts_webui_extension_vox_cpm-0.0.1.dist-info/licenses/LICENSE
tts_webui_extension_vox_cpm-0.0.1.dist-info/METADATA
tts_webui_extension_vox_cpm-0.0.1.dist-info/WHEEL
tts_webui_extension_vox_cpm-0.0.1.dist-info/top_level.txt
tts_webui_extension_vox_cpm-0.0.1.dist-info/RECORD
