Metadata-Version: 2.4
Name: tts_webui_extension.vox_cpm
Version: 0.0.1
Summary: A template extension for TTS Generation WebUI
Home-page: https://github.com/rsxdalv/tts_webui_extension.vox_cpm
Author: OpenBMB
Classifier: Programming Language :: Python :: 3
Classifier: License :: OSI Approved :: MIT License
Classifier: Operating System :: OS Independent
License-File: LICENSE
Requires-Dist: voxcpm
Dynamic: author
Dynamic: classifier
Dynamic: description
Dynamic: description-content-type
Dynamic: home-page
Dynamic: license-file
Dynamic: requires-dist
Dynamic: summary
